todoinator/__init__.py
todoinator/todoinator.py
todoinator-0.0.1.data/scripts/todoinator
todoinator-0.0.1.dist-info/DESCRIPTION.rst
todoinator-0.0.1.dist-info/METADATA
todoinator-0.0.1.dist-info/RECORD
todoinator-0.0.1.dist-info/WHEEL
todoinator-0.0.1.dist-info/metadata.json
todoinator-0.0.1.dist-info/top_level.txt
