Metadata-Version: 2.0
Name: todoinator
Version: 0.0.1
Summary: Extract todo info from code.
Home-page: UNKNOWN
Author: Paul R. Brian <paul@mikadosoftware.com>
Author-email: UNKNOWN
License: UNKNOWN
Platform: UNKNOWN
